bfabric_scripts/__init__.py
bfabric_scripts/bfabric_executable_submitter_functionalTest.py
bfabric_scripts/bfabric_executable_submitter_gridengine.py
bfabric_scripts/bfabric_executable_submitter_slurm.py
bfabric_scripts/bfabric_executable_wrappercreator.py
bfabric_scripts/bfabric_feeder_mascot.py
bfabric_scripts/bfabric_flask.py
bfabric_scripts/bfabric_list_not_existing_storage_directories.py
bfabric_scripts/bfabric_list_workunit_parameters.py
bfabric_scripts/bfabric_logthis.py
bfabric_scripts/bfabric_read.py
bfabric_scripts/bfabric_read_samples_from_dataset.py
bfabric_scripts/bfabric_read_samples_of_workunit.py
bfabric_scripts/bfabric_save_csv2dataset.py
bfabric_scripts/bfabric_save_dataset2csv.py
bfabric_scripts/bfabric_save_fasta.py
bfabric_scripts/bfabric_save_importresource_sample.py
bfabric_scripts/bfabric_save_link_to_workunit.py
bfabric_scripts/bfabric_save_resource_description.py
bfabric_scripts/bfabric_save_workflowstep.py
bfabric_scripts/bfabric_save_workunit_attribute.py
bfabric_scripts/bfabric_setExternalJobStatus_done.py
bfabric_scripts/bfabric_setResourceStatus_available.py
bfabric_scripts/bfabric_setWorkunitStatus.py
bfabric_scripts/bfabric_slurm_queue_status.py
bfabric_scripts/bfabric_upload_resource.py
bfabric_scripts/bfabric_upload_submitter_executable.py
bfabric_scripts/bfabric_wrapper_creator_yaml.py
bfabric_scripts/fgcz_maxquant_scaffold-wrapper.py
bfabric_scripts/fgcz_maxquant_wrapper.py
bfabric_scripts/fgcz_sge_maxquant_linux.bash
bfabric_scripts/optional_features.py
bfabric_scripts/py.typed
bfabric_scripts/cli/__init__.py
bfabric_scripts/cli/__main__.py
bfabric_scripts/cli/cli_api.py
bfabric_scripts/cli/cli_dataset.py
bfabric_scripts/cli/cli_executable.py
bfabric_scripts/cli/cli_external_job.py
bfabric_scripts/cli/cli_feeder.py
bfabric_scripts/cli/cli_workunit.py
bfabric_scripts/cli/api/__init__.py
bfabric_scripts/cli/api/create.py
bfabric_scripts/cli/api/delete.py
bfabric_scripts/cli/api/inspect.py
bfabric_scripts/cli/api/namespaces.py
bfabric_scripts-1.13.40.dist-info/METADATA
bfabric_scripts-1.13.40.dist-info/WHEEL
bfabric_scripts-1.13.40.dist-info/entry_points.txt
bfabric_scripts-1.13.40.dist-info/RECORD
