Metadata-Version: 2.4
Name: bfabric_scripts
Version: 1.13.40
Summary: Python command line scripts for the B-Fabric API
Requires-Python: >=3.11
Requires-Dist: bfabric<2,>=1.16.1
Requires-Dist: cyclopts<5.0,>=4.0
Requires-Dist: flask<4.0,>=3.0.3
Requires-Dist: xmltodict<2.0.0,>=1.0.0
Provides-Extra: excel
Requires-Dist: fastexcel>=0.18.0; extra == 'excel'
Provides-Extra: test
Requires-Dist: freezegun>=1.5.5; extra == 'test'
Requires-Dist: inline-snapshot>=0.30.0; extra == 'test'
Requires-Dist: logot[loguru,pytest]>=1.3.0; extra == 'test'
Requires-Dist: pyfakefs>=5.10.0; extra == 'test'
Requires-Dist: pytest-mock>=3.15.1; extra == 'test'
Requires-Dist: pytest>=8.4.2; extra == 'test'
